kolesky/__init__.py
kolesky/cholesky.py
kolesky/kl_cholesky.py
kolesky/maxheap.c
kolesky/maxheap.cpython-311-x86_64-linux-gnu.so
kolesky/maxheap.pxd
kolesky/maxheap.pyx
kolesky/mkl.pxd
kolesky/ordering.c
kolesky/ordering.cpython-311-x86_64-linux-gnu.so
kolesky/ordering.pyx
kolesky.libs/libmkl_core-9861e321.so.2
kolesky.libs/libmkl_intel_lp64-2bc1202b.so.2
kolesky.libs/libmkl_intel_thread-6afedd3d.so.2
kolesky.libs/libomp-420f2663.so
kolesky-0.1.3.dist-info/METADATA
kolesky-0.1.3.dist-info/WHEEL
kolesky-0.1.3.dist-info/top_level.txt
kolesky-0.1.3.dist-info/RECORD
