Metadata-Version: 2.2
Name: kolesky
Version: 0.1.3
Author: Raymond Zeng
Author-email: Raymond Zeng <rzeng42@gatech.edu>
Requires-Python: >=3.10
Requires-Dist: numpy
Requires-Dist: scipy
Requires-Dist: scikit-learn
Requires-Dist: mkl>=2021.4.0
Dynamic: author
